genomic_features/__init__.py
genomic_features/filters.py
genomic_features/_core/cache.py
genomic_features/_core/filters.py
genomic_features/ensembl/__init__.py
genomic_features/ensembl/ensembldb.py
genomic_features-0.0.1a0.dist-info/METADATA
genomic_features-0.0.1a0.dist-info/WHEEL
genomic_features-0.0.1a0.dist-info/licenses/LICENSE
genomic_features-0.0.1a0.dist-info/RECORD
