Metadata-Version: 2.1
Name: genomic-features
Version: 0.0.1a0
Summary: Genomic annotations using BioConductor resources in Python.
Project-URL: Documentation, https://genomic-features.readthedocs.io/
Project-URL: Source, https://github.com/scverse/genomic-features
Project-URL: Home-page, https://github.com/scverse/genomic-features
Author: Isaac Virshup, Emma Dann, Laura Martens
Maintainer-email: Isaac Virshup <ivirshup@gmail.com>, Emma Dann <ed6@sanger.ac.uk>, Laura Martens <laura.d.martens@icloud.com>
License: BSD 3-Clause License
License-File: LICENSE
Requires-Python: >=3.9
Requires-Dist: ibis-framework[sqlite]
Requires-Dist: pandas
Requires-Dist: pooch
Requires-Dist: pyarrow
Requires-Dist: session-info
Provides-Extra: dev
Requires-Dist: bump2version; extra == 'dev'
Requires-Dist: pre-commit; extra == 'dev'
Requires-Dist: twine>=4.0.2; extra == 'dev'
Provides-Extra: doc
Requires-Dist: ipykernel; extra == 'doc'
Requires-Dist: ipython; extra == 'doc'
Requires-Dist: myst-nb; extra == 'doc'
Requires-Dist: sphinx-autodoc-typehints; extra == 'doc'
Requires-Dist: sphinx-book-theme>=1.0.0; extra == 'doc'
Requires-Dist: sphinx-copybutton; extra == 'doc'
Requires-Dist: sphinx>=4; extra == 'doc'
Requires-Dist: sphinxcontrib-bibtex>=1.0.0; extra == 'doc'
Provides-Extra: test
Requires-Dist: pytest; extra == 'test'
Requires-Dist: pytest-cov; extra == 'test'
